pymscada_html/__init__.py
pymscada_html/config.py
pymscada_html/html/3rdpartylicenses.txt
pymscada_html/html/LICENSE
pymscada_html/html/__init__.py
pymscada_html/html/favicon.ico
pymscada_html/html/index.html
pymscada_html/html/main.a264448cc934d301.js
pymscada_html/html/polyfills.7fa86ca1817267a3.js
pymscada_html/html/robots.txt
pymscada_html/html/runtime.b3a744f938a06280.js
pymscada_html/html/styles.49369c0ad90094ec.css
pymscada_html/html/__pycache__/__init__.cpython-311.pyc
pymscada_html-0.2.5.dist-info/licenses/LICENSE
pymscada_html-0.2.5.dist-info/METADATA
pymscada_html-0.2.5.dist-info/WHEEL
pymscada_html-0.2.5.dist-info/top_level.txt
pymscada_html-0.2.5.dist-info/RECORD
