Metadata-Version: 2.4
Name: pymscada-html
Version: 0.2.5
Summary: Angular single page application html files served by pymscada.
Author-email: Jamie Walton <jamie@walton.net.nz>
License: GPL-3.0-or-later
Project-URL: Homepage, https://github.com/jamie0walton/pymscada-html
Project-URL: Bug Tracker, https://github.com/jamie0walton/pymscada-html/issues
Classifier: Programming Language :: Python :: 3
Classifier: Programming Language :: JavaScript
Classifier: License :: OSI Approved :: GNU General Public License v3 (GPLv3)
Classifier: Operating System :: OS Independent
Classifier: Environment :: Console
Classifier: Development Status :: 1 - Planning
Requires-Python: >=3.9
License-File: LICENSE
Dynamic: license-file
